django-celery-task-trigger/__init__.py
django-celery-task-trigger/task_trigger.py
django_celery_task_trigger/__init__.py
django_celery_task_trigger/task_trigger.py
django_celery_task_trigger-0.1.0.dist-info/METADATA
django_celery_task_trigger-0.1.0.dist-info/RECORD
django_celery_task_trigger-0.1.0.dist-info/WHEEL
django_celery_task_trigger-0.1.0.dist-info/top_level.txt
