Metadata-Version: 2.1
Name: django-celery-task-trigger
Version: 0.1.0
Summary: Dynamic Task trigger for django-celery-task-broker 
Home-page: https://github.com/lifez/django-celery-task-trigger
Author: Prontotools
Author-email: prontotools@prontomarketing.com
License: MIT
Platform: UNKNOWN
Classifier: Framework :: Django
Classifier: Topic :: Software Development :: Object Brokering
Classifier: Topic :: System :: Distributed Computing
Classifier: Topic :: Utilities
Classifier: License :: OSI Approved :: MIT License
Classifier: Programming Language :: Python :: 3.6
Requires-Dist: requests (>=2.19.1)
